pkgver/__init__.py
scora_notify/__init__.py
scora_notify/event_tracker.py
scora_notify/notify.py
scora_notify-0.7.0.dist-info/METADATA
scora_notify-0.7.0.dist-info/WHEEL
scora_notify-0.7.0.dist-info/top_level.txt
scora_notify-0.7.0.dist-info/zip-safe
scora_notify-0.7.0.dist-info/RECORD
