Metadata-Version: 2.1
Name: scora-notify
Version: 0.7.0
Summary: Scora Slack notification lib
Author: Oncase
Author-email: contato@oncase.com.br
Keywords: scora
Classifier: Intended Audience :: Developers
Classifier: Natural Language :: English
Classifier: Programming Language :: Python :: 3.6
Requires-Dist: slack-sdk (>=3.19.1)
Requires-Dist: mixpanel (>=4.10.0)
Provides-Extra: dev
Requires-Dist: twine (>=3.1.1) ; extra == 'dev'
Requires-Dist: Sphinx (==3.1.1) ; extra == 'dev'
Requires-Dist: sphinxcontrib-napoleon (==0.7) ; extra == 'dev'
Requires-Dist: sphinx-rtd-theme (==0.5.0) ; extra == 'dev'
Requires-Dist: sphinx-click (==2.3.2) ; extra == 'dev'
Requires-Dist: flake8 (==3.8.3) ; extra == 'dev'
